Metadata-Version: 2.1
Name: core-module-blob-host-app
Version: 2.19.0
Summary: Blob Host module for the parser core project
Home-page: https://github.com/usnistgov/core_module_blob_host_app
Author: NIST IT Lab
Author-email: itl_inquiries@nist.gov
License-File: LICENSE.md
